krake/__init__.py
krake/test_utils.py
krake/utils.py
krake/api/__init__.py
krake/api/__main__.py
krake/api/app.py
krake/api/auth.py
krake/api/core.py
krake/api/database.py
krake/api/helpers.py
krake/api/infrastructure.py
krake/api/kubernetes.py
krake/api/middlewares.py
krake/api/openstack.py
krake/client/__init__.py
krake/client/core.py
krake/client/infrastructure.py
krake/client/kubernetes.py
krake/client/openstack.py
krake/controller/__init__.py
krake/controller/gc.py
krake/controller/magnum.py
krake/controller/infrastructure/__init__.py
krake/controller/infrastructure/__main__.py
krake/controller/infrastructure/infrastructure.py
krake/controller/infrastructure/providers.py
krake/controller/kubernetes/__init__.py
krake/controller/kubernetes/client.py
krake/controller/kubernetes/hooks.py
krake/controller/kubernetes/tosca.py
krake/controller/kubernetes/application/__init__.py
krake/controller/kubernetes/application/__main__.py
krake/controller/kubernetes/application/application.py
krake/controller/kubernetes/cluster/__init__.py
krake/controller/kubernetes/cluster/__main__.py
krake/controller/kubernetes/cluster/cluster.py
krake/controller/scheduler/__init__.py
krake/controller/scheduler/__main__.py
krake/controller/scheduler/constraints.py
krake/controller/scheduler/metrics.py
krake/controller/scheduler/scheduler.py
krake/data/__init__.py
krake/data/config.py
krake/data/constraints.py
krake/data/core.py
krake/data/infrastructure.py
krake/data/kubernetes.py
krake/data/openstack.py
krake/data/serializable.py
krake-1.0.1.data/scripts/krake_bootstrap_db
krake-1.0.1.data/scripts/krake_generate_config
tests/__init__.py
tests/conftest.py
tests/api/__init__.py
tests/api/test_app.py
tests/api/test_auth.py
tests/api/test_config.py
tests/api/test_core.py
tests/api/test_database.py
tests/api/test_etcd.py
tests/api/test_helpers.py
tests/api/test_infrastructure.py
tests/api/test_kubernetes.py
tests/api/test_openstack.py
tests/client/__init__.py
tests/client/test_core.py
krake-1.0.1.dist-info/LICENSE
krake-1.0.1.dist-info/METADATA
krake-1.0.1.dist-info/WHEEL
krake-1.0.1.dist-info/top_level.txt
krake-1.0.1.dist-info/RECORD
